mozleak/__init__.py
mozleak/leaklog.py
mozleak/lsan.py
mozleak-0.2.dist-info/METADATA
mozleak-0.2.dist-info/WHEEL
mozleak-0.2.dist-info/top_level.txt
mozleak-0.2.dist-info/RECORD
